[
  {
    "image": "../images/gallery-project-basket.jpg",
    "title": "TL Yarncrafts CAL Basket",
    "pillar": "Maker's Studio",
    "description": "A useful stash basket worked in the round with bulky yarn held in two strands, using the waistcoat stitch",
    "tags": [
      "home decor",
      "waistcoat stitch",
      "bulky acrylic"
    ]
  },
  {
    "image": "../images/flower-mandala-earrings.jpg",
    "title": "Flower Mandala Earrings",
    "pillar": "Collector's Vault",
    "description": "Crocheted earrings with 7-petal flowers, reinforced with wire, and a small bead at the tip of each petal.",
    "tags": [
      "jewelry",
      "bead crochet",
      "fine yarn/lace"
    ]
  },
  {
    "image": "../images/hyperbolic-coral-charm.jpg",
    "title": "Hyperbolic Plane Coral ball charm",
    "pillar": "Collector's Vault",
    "description": "Started as a round, disc-shaped ring and increasing stitches exponentially, this coral-like shape proves that hyperbolic planes (surfaces with negative curvature) can actually be physically created - with crochet!",
    "tags": [
      "accessories",
      "geometry crochet",
      "fine cotton"
    ]
  }
]
